nova/__init__.py
nova/cli.py
nova/cli_fixed.py
nova/config.py
nova/config_loader.py
nova/logger.py
nova/agent/__init__.py
nova/agent/deep_agent.py
nova/agent/llm_agent.py
nova/agent/llm_agent_enhanced.py
nova/agent/llm_client.py
nova/agent/llm_client_complete_fix.py
nova/agent/llm_client_fixed.py
nova/agent/mock_llm.py
nova/agent/state.py
nova/nodes/__init__.py
nova/nodes/actor.py
nova/nodes/apply_patch.py
nova/nodes/critic.py
nova/nodes/planner.py
nova/nodes/reflect.py
nova/nodes/run_tests.py
nova/runner/__init__.py
nova/runner/test_runner.py
nova/telemetry/__init__.py
nova/tools/__init__.py
nova/tools/datetime_utils.py
nova/tools/doctor.py
nova/tools/doctor_cli.py
nova/tools/fs.py
nova/tools/git.py
nova/tools/http.py
nova/tools/lock.py
nova/tools/model_selector.py
nova/tools/patch_fixer.py
nova/tools/pr_generator.py
nova/tools/safety_limits.py
nova/tools/sandbox.py
nova/tools/test_pr.py
nova_ci_rescue-1.1.0.dist-info/licenses/AUTHORS.md
nova_ci_rescue-1.1.0.dist-info/licenses/LICENSE
nova_ci_rescue-1.1.0.dist-info/METADATA
nova_ci_rescue-1.1.0.dist-info/WHEEL
nova_ci_rescue-1.1.0.dist-info/entry_points.txt
nova_ci_rescue-1.1.0.dist-info/top_level.txt
nova_ci_rescue-1.1.0.dist-info/RECORD
