Metadata-Version: 2.4
Name: nova-ci-rescue
Version: 1.1.0
Summary: AlwaysGreen: Self-healing CI/CD autopatcher
Author-email: AlwaysGreen Contributors <support@alwaysgreen.ai>
License-Expression: MIT
Project-URL: Homepage, https://github.com/novasolve/nova-ci-rescue
Project-URL: Repository, https://github.com/novasolve/nova-ci-rescue
Project-URL: Issues, https://github.com/novasolve/nova-ci-rescue/issues
Project-URL: Documentation, https://github.com/novasolve/nova-ci-rescue/tree/main/docs
Keywords: ci,cd,testing,automation,ai,llm,pytest,github-actions
Classifier: Development Status :: 4 - Beta
Classifier: Intended Audience :: Developers
Classifier: Programming Language :: Python :: 3
Classifier: Programming Language :: Python :: 3.10
Classifier: Programming Language :: Python :: 3.11
Classifier: Programming Language :: Python :: 3.12
Classifier: Topic :: Software Development :: Testing
Classifier: Topic :: Software Development :: Quality Assurance
Requires-Python: >=3.10
License-File: LICENSE
License-File: AUTHORS.md
Requires-Dist: pydantic>=2.0.0
Requires-Dist: python-dotenv>=1.0.0
Requires-Dist: httpx>=0.25.0
Requires-Dist: typer[all]>=0.9.0
Requires-Dist: rich>=13.0.0
Requires-Dist: GitPython>=3.1.0
Requires-Dist: PyYAML>=6.0
Provides-Extra: dev
Requires-Dist: pytest>=7.0; extra == "dev"
Requires-Dist: pytest-asyncio; extra == "dev"
Requires-Dist: pytest-json-report; extra == "dev"
Requires-Dist: black; extra == "dev"
Requires-Dist: ruff; extra == "dev"
Dynamic: license-file
